ns_gradient/__init__.py
ns_gradient/nsgrads.py
ns_gradient/test.py
ns_gradient-0.0.2.dist-info/LICENSE
ns_gradient-0.0.2.dist-info/METADATA
ns_gradient-0.0.2.dist-info/WHEEL
ns_gradient-0.0.2.dist-info/top_level.txt
ns_gradient-0.0.2.dist-info/RECORD
