Metadata-Version: 2.1
Name: ns-gradient
Version: 0.0.2
Summary: A package for calculating shifted gradients
Home-page: https://nkrtech.com
Author: Nicolus Rotich
Author-email: nicholas.rotich@gmail.com
License: MIT
Download-URL: https://github.com/moinonin/ns_gradient/archive/refs/heads/main.zip
Project-URL: Bug Tracker, https://github.com/pypa/ns_gradient/issues
Platform: any
Classifier: License :: OSI Approved :: MIT License
Requires-Python: >3.8
License-File: LICENSE
Requires-Dist: setuptools>=58.1.0
Requires-Dist: wheel>=0.37.1
Requires-Dist: numpy>=1.26.3
Requires-Dist: pandas>=2.1.4
Requires-Dist: fire
